<?xml version='1.0'?><stations><station><slat>35.2361</slat><slong>-88.3911</slong><sname>Hollingsworth Pitstop</sname><saddress>202 E Main St</saddress><scity>Adamsville</scity><sstate>TN</sstate><sbrand>UNBRANDED</sbrand><soctane>87 89 93</soctane></station><station><slat>35.78515</slat><slong>-89.11625</slong><sname>Service Center</sname><saddress>Main St</saddress><scity>Alamo</scity><sstate>TN</sstate><sbrand>UNBRANDED</sbrand><soctane>93</soctane></station><station><slat>36.38087</slat><slong>-84.88463</slong><sname>Burnett's Fuel Center</sname><saddress>1901 Michigan St.</saddress><scity>Allardt</scity><sstate>TN</sstate><sbrand>UNBRANDED</sbrand><soctane>87 93</soctane></station><station><slat>36.20299</slat><slong>-84.0316</slong><sname>Cornerstone Market &amp; Deli</sname><saddress>1104 Park Lane</saddress><scity>Andersonville</scity><sstate>TN</sstate><sbrand>UNBRANDED</sbrand><soctane></soctane></station><station><slat>36.2012</slat><slong>-84.0325</slong><sname>Sharp Hardware</sname><saddress>4011 Andersonville Highway</saddress><scity>Andersonville</scity><sstate>TN</sstate><sbrand>UNBRANDED</sbrand><soctane>87 89 91</soctane></station><station><slat>36.08793</slat><slong>-86.60738</slong><sname>Mapco Mart</sname><saddress>2827 Smith Springs Road</saddress><scity>Antioch</scity><sstate>TN</sstate><sbrand>MAPCO</sbrand><soctane>87 89 93</soctane></station><station><slat>36.20409</slat><slong>-86.99156</slong><sname>Teter's Market</sname><saddress>3505 River Road</saddress><scity>Ashland City</scity><sstate>TN</sstate><sbrand>UNBRANDED</sbrand><soctane>87 93</soctane></station><station><slat>36.2344</slat><slong>-87.05679</slong><sname>Lakeview Market</sname><saddress>1910 River Road</saddress><scity>Ashland City</scity><sstate>TN</sstate><sbrand>UNBRANDED</sbrand><soctane></soctane></station><station><slat>36.29539</slat><slong>-87.00443</slong><sname>Oranges Market</sname><saddress>1900 Bearwallow Road</saddress><scity>Ashland City</scity><sstate>TN</sstate><sbrand>UNBRANDED</sbrand><soctane>87 89 92</soctane></station><station><slat>35.43813</slat><slong>-84.59045</slong><sname>Citgo Mart  ( White St</sname><saddress>405 S. White St</saddress><scity>Athens</scity><sstate>TN</sstate><sbrand>CITGO</sbrand><soctane>87</soctane></station><station><slat>36.06251</slat><slong>-85.65231</slong><sname>Little Dodge Market</sname><saddress>8506 Cookeville Boat Dock Rd</saddress><scity>Baxter</scity><sstate>TN</sstate><sbrand>UNBRANDED</sbrand><soctane>87 93</soctane></station><station><slat>35.27548</slat><slong>-85.39358</slong><sname>Beersheba Springs Market</sname><saddress>Highway 56</saddress><scity>Beersheba Springs</scity><sstate>TN</sstate><sbrand>UNBRANDED</sbrand><soctane>87</soctane></station><station><slat>35.64942</slat><slong>-86.42536</slong><sname>Dj's Market</sname><saddress>4011 U.S. 231</saddress><scity>Bell Buckle</scity><sstate>TN</sstate><sbrand>PURE</sbrand><soctane>90</soctane></station><station><slat>35.106</slat><slong>-86.2017</slong><sname>Ashley's Family Market</sname><saddress>8791 David Crockett Hwy (U S 64)</saddress><scity>Belvidere</scity><sstate>TN</sstate><sbrand>UNBRANDED</sbrand><soctane>87 89 93</soctane></station><station><slat>35.93718</slat><slong>-87.29411</slong><sname>T&amp;J Short Stop Market</sname><saddress>9676 Hwy 46</saddress><scity>Bon Aqua</scity><sstate>TN</sstate><sbrand>UNBRANDED</sbrand><soctane>87 89 92</soctane></station><station><slat>35.93223</slat><slong>-87.21835</slong><sname>Country Quickstop</sname><saddress>7328 Highway 100</saddress><scity>Bon Aqua</scity><sstate>TN</sstate><sbrand>UNBRANDED</sbrand><soctane>87 89 92</soctane></station><station><slat>36.5925</slat><slong>-82.17617</slong><sname>Quick Mart</sname><saddress>201 Pennsylvania Avenue</saddress><scity>Bristol</scity><sstate>TN</sstate><sbrand>SUNOCO</sbrand><soctane>87 89 93</soctane></station><station><slat>36.58034</slat><slong>-82.23741</slong><sname>R &amp; T Discount Tobacco</sname><saddress>879 Highway 126</saddress><scity>Bristol</scity><sstate>TN</sstate><sbrand>UNBRANDED</sbrand><soctane>87 89 93</soctane></station><station><slat>36.55527</slat><slong>-82.28066</slong><sname>A&amp;R Big Orange Mkt</sname><saddress>2142 Tennessee Hwy 126</saddress><scity>Bristol</scity><sstate>TN</sstate><sbrand>CITGO</sbrand><soctane>87 89 93</soctane></station><station><slat>36.55634</slat><slong>-82.17772</slong><sname>Cedar Creek Handy Market</sname><saddress>2117-B Weaver Pike</saddress><scity>Bristol</scity><sstate>TN</sstate><sbrand>UNBRANDED</sbrand><soctane>87 89 93</soctane></station><station><slat>35.56037</slat><slong>-89.77009</slong><sname>59 Express</sname><saddress>7140 Highway 59 W</saddress><scity>Burlison</scity><sstate>TN</sstate><sbrand>UNBRANDED</sbrand><soctane>93</soctane></station><station><slat>36.29443</slat><slong>-82.0135</slong><sname>Elk Mills General Store</sname><saddress>5630 Hwy. 321</saddress><scity>Butler</scity><sstate>TN</sstate><sbrand>UNBRANDED</sbrand><soctane>87 89 93</soctane></station><station><slat>36.59183</slat><slong>-85.12434</slong><sname>111 One Stop</sname><saddress>9125 Highway 111</saddress><scity>Byrdstown</scity><sstate>TN</sstate><sbrand>CONOCO</sbrand><soctane>87 90 93</soctane></station><station><slat>36.0581</slat><slong>-88.1049</slong><sname>Camden Phillips 66</sname><saddress>169 W. Main</saddress><scity>Camden</scity><sstate>TN</sstate><sbrand>PHILLIPS</sbrand><soctane>87 89 92</soctane></station><station><slat>36.02332</slat><slong>-88.06429</slong><sname>Big Daddy</sname><saddress>4585 Hwy 70 East</saddress><scity>Camden</scity><sstate>TN</sstate><sbrand>CONOCO</sbrand><soctane>86 89 94</soctane></station><station><slat>36.55681</slat><slong>-85.51866</slong><sname>Happy Sack</sname><saddress>1005 Clay County Hwy</saddress><scity>Celina</scity><sstate>TN</sstate><sbrand>PHILLIPS</sbrand><soctane>87 89 93</soctane></station><station><slat>35.6968</slat><slong>-86.69454</slong><sname>Holt's Corner Quick Stop</sname><saddress>6261 Nashville Hwy</saddress><scity>Chapel Hill</scity><sstate>TN</sstate><sbrand>UNBRANDED</sbrand><soctane>87 89 93</soctane></station><station><slat>35.09677</slat><slong>-85.32783</slong><sname>Midnite Oil</sname><saddress>627a Signal Mtn Rd</saddress><scity>Chattanooga</scity><sstate>TN</sstate><sbrand>UNBRANDED</sbrand><soctane>87 93</soctane></station><station><slat>35.08067</slat><slong>-85.21506</slong><sname>Allen's Stop &amp; Go</sname><saddress>4266 Bonny Oaks Dr</saddress><scity>Chattanooga</scity><sstate>TN</sstate><sbrand>PURE</sbrand><soctane>87 89 93</soctane></station><station><slat>35.01481</slat><slong>-85.16356</slong><sname>Midnite Oil</sname><saddress>7355 East Brainerd &amp; Gunbarrel Rd.</saddress><scity>Chattanooga</scity><sstate>TN</sstate><sbrand>UNBRANDED</sbrand><soctane>89 93</soctane></station><station><slat>35.01662</slat><slong>-85.27304</slong><sname>Kankus</sname><saddress>2115 Dodds Ave</saddress><scity>Chattanooga</scity><sstate>TN</sstate><sbrand>SMILE</sbrand><soctane>87 92</soctane></station><station><slat>34.99763</slat><slong>-85.29145</slong><sname>Midnite Oil</sname><saddress>4004 Rossville Blvd</saddress><scity>Chattanooga</scity><sstate>TN</sstate><sbrand>UNBRANDED</sbrand><soctane>89 93</soctane></station><station><slat>35.04627</slat><slong>-85.16625</slong><sname>Hi-Tech / Jay's Food Mart</sname><saddress>6800 Shallowford Rd</saddress><scity>Chattanooga</scity><sstate>TN</sstate><sbrand>HI-TECH</sbrand><soctane>87</soctane></station><station><slat>35.01145</slat><slong>-85.15704</slong><sname>Kankus</sname><saddress>7640 E Brainerd Rd</saddress><scity>Chattanooga</scity><sstate>TN</sstate><sbrand>SMILE</sbrand><soctane>93</soctane></station><station><slat>35.00551</slat><slong>-85.12216</slong><sname>Quickmart</sname><saddress>9117 E. Brainerd Rd</saddress><scity>Chattanooga</scity><sstate>TN</sstate><sbrand>UNBRANDED</sbrand><soctane></soctane></station><station><slat>35.03417</slat><slong>-85.13345</slong><sname>Kankus</sname><saddress>Shallowford And Jenkins Rd</saddress><scity>Chattanooga</scity><sstate>TN</sstate><sbrand>SMILE</sbrand><soctane>87</soctane></station><station><slat>35.07398</slat><slong>-85.19218</slong><sname>Midnite Oil</sname><saddress>4833 Bonny Oaks Drive</saddress><scity>Chattanooga</scity><sstate>TN</sstate><sbrand>UNBRANDED</sbrand><soctane>87 89 93</soctane></station><station><slat>34.98948</slat><slong>-85.20915</slong><sname>Tip Top Mart</sname><saddress>6500 Ringgold Rd.</saddress><scity>Chattanooga / East Ridge</scity><sstate>TN</sstate><sbrand>UNBRANDED</sbrand><soctane>87 89 93</soctane></station><station><slat>35.13521</slat><slong>-85.28075</slong><sname>Red Bank Service Center</sname><saddress>4720 Dayton Blvd</saddress><scity>Chattanooga / Red Bank</scity><sstate>TN</sstate><sbrand>PURE</sbrand><soctane>87 89 93</soctane></station><station><slat>35.1223</slat><slong>-85.343</slong><sname>Espresso Mart</sname><saddress>816 Ridgeway Terrace</saddress><scity>Chattanooga / Signal Mountain</scity><sstate>TN</sstate><sbrand>UNBRANDED</sbrand><soctane>87 89 93</soctane></station><station><slat>36.52868</slat><slong>-87.36389</slong><sname>Hi-Lo</sname><saddress>261 North Riverside Drive</saddress><scity>Clarksville</scity><sstate>TN</sstate><sbrand>BEACH</sbrand><soctane>87</soctane></station><station><slat>36.55118</slat><slong>-87.41124</slong><sname>Quick Pump Shop</sname><saddress>411 Dover Road</saddress><scity>Clarksville</scity><sstate>TN</sstate><sbrand>UNBRANDED</sbrand><soctane>89 91</soctane></station><station><slat>36.51591</slat><slong>-87.25054</slong><sname>Beach Oil Company</sname><saddress>631 Hwy 76</saddress><scity>Clarksville</scity><sstate>TN</sstate><sbrand>BEACH</sbrand><soctane>87 93</soctane></station><station><slat>36.55403</slat><slong>-87.32438</slong><sname>Montgomery Farmers Co-Op</sname><saddress>1801 Wilma Rudolph Boulevard</saddress><scity>Clarksville</scity><sstate>TN</sstate><sbrand>UNBRANDED</sbrand><soctane>87 89 92</soctane></station><station><slat>35.13112</slat><slong>-84.74048</slong><sname>One Stop Shop</sname><saddress>6658 Waterlevel Hwy</saddress><scity>Cleveland</scity><sstate>TN</sstate><sbrand>UNBRANDED</sbrand><soctane>87 89 93</soctane></station><station><slat>35.19018</slat><slong>-84.88181</slong><sname>Chevron</sname><saddress>1420 25th St.</saddress><scity>Cleveland</scity><sstate>TN</sstate><sbrand>UNBRANDED</sbrand><soctane>87</soctane></station><station><slat>35.13092</slat><slong>-84.86402</slong><sname>Hi-Tech</sname><saddress>Apd 40 At Mcgrady Dr Se</saddress><scity>Cleveland</scity><sstate>TN</sstate><sbrand>HI-TECH</sbrand><soctane>87</soctane></station><station><slat>35.13163</slat><slong>-84.87035</slong><sname>P &amp; M Station Apd 40</sname><saddress>2274 Dalton Pike</saddress><scity>Cleveland</scity><sstate>TN</sstate><sbrand>AMERICAN</sbrand><soctane>85</soctane></station><station><slat>35.14535</slat><slong>-84.92216</slong><sname>Fuel Mart #4</sname><saddress>2480 South Lee Hwy Sw</saddress><scity>Cleveland</scity><sstate>TN</sstate><sbrand>UNBRANDED</sbrand><soctane>93</soctane></station><station><slat>35.12213</slat><slong>-84.84685</slong><sname>Fuel Mart</sname><saddress>Wildwood At Springplace Rd</saddress><scity>Cleveland</scity><sstate>TN</sstate><sbrand>UNBRANDED</sbrand><soctane>87</soctane></station><station><slat>35.18061</slat><slong>-84.86187</slong><sname>Hi-Tech Eagle Express</sname><saddress>2902 N Ocoee St</saddress><scity>Cleveland</scity><sstate>TN</sstate><sbrand>HI-TECH</sbrand><soctane>87</soctane></station><station><slat>35.14222</slat><slong>-84.87131</slong><sname>Quick Chek</sname><saddress>1703 Wildwood Ave. Se</saddress><scity>Cleveland</scity><sstate>TN</sstate><sbrand>UNBRANDED</sbrand><soctane>86 89 92</soctane></station><station><slat>36.03416</slat><slong>-84.41546</slong><sname>Coalfield Market And Deli</sname><saddress>5707 Knoxville Hwy</saddress><scity>Coalfield</scity><sstate>TN</sstate><sbrand>UNBRANDED</sbrand><soctane>87</soctane></station><station><slat>35.8083</slat><slong>-86.66243</slong><sname>Joe Kelly's Market</sname><saddress>8351 Horton Hwy</saddress><scity>College Grove</scity><sstate>TN</sstate><sbrand>UNBRANDED</sbrand><soctane>87</soctane></station><station><slat>35.61778</slat><slong>-87.06169</slong><sname>Columbia Oil Company</sname><saddress>1100 Hampshire Pike</saddress><scity>Columbia</scity><sstate>TN</sstate><sbrand>UNBRANDED</sbrand><soctane></soctane></station><station><slat>35.6116</slat><slong>-87.03556</slong><sname>Hardison's Grocery</sname><saddress>1002 Carmack Blvd.</saddress><scity>Columbia</scity><sstate>TN</sstate><sbrand>UNBRANDED</sbrand><soctane>87 89 92</soctane></station><station><slat>35.60072</slat><slong>-87.03623</slong><sname>Kwik Sak</sname><saddress>1800 Carmack Blvd</saddress><scity>Columbia</scity><sstate>TN</sstate><sbrand>UNBRANDED</sbrand><soctane>87 89 92</soctane></station><station><slat>35.62708</slat><slong>-87.04859</slong><sname>Kwik Sak 609</sname><saddress>401 S James Campbell Blvd</saddress><scity>Columbia</scity><sstate>TN</sstate><sbrand>UNBRANDED</sbrand><soctane>87 89 92</soctane></station><station><slat>36.12759</slat><slong>-85.48117</slong><sname>Sunoco</sname><saddress>1200 Dacco Drive</saddress><scity>Cookeville</scity><sstate>TN</sstate><sbrand>SUNOCO</sbrand><soctane>86 89 92</soctane></station><station><slat>36.18592</slat><slong>-85.50716</slong><sname>Bread Box Market</sname><saddress>1875 North Dixie Avenue</saddress><scity>Cookeville</scity><sstate>TN</sstate><sbrand>UNBRANDED</sbrand><soctane>86 92</soctane></station><station><slat>36.37279</slat><slong>-85.64209</slong><sname>Roy's Market</sname><saddress>5711 Dodson Branch Road</saddress><scity>Cookeville</scity><sstate>TN</sstate><sbrand>UNBRANDED</sbrand><soctane>87 89 93</soctane></station><station><slat>36.17194</slat><slong>-85.51176</slong><sname>Citgo</sname><saddress>660 North Willow Avenue</saddress><scity>Cookeville</scity><sstate>TN</sstate><sbrand>CITGO</sbrand><soctane>87 89 91</soctane></station><station><slat>36.17312</slat><slong>-85.54003</slong><sname>Lead Lap</sname><saddress>1388 West Broad Street</saddress><scity>Cookeville</scity><sstate>TN</sstate><sbrand>SUNOCO</sbrand><soctane>93</soctane></station><station><slat>36.12064</slat><slong>-83.85306</slong><sname>Weigel's</sname><saddress>7420 Tazewell Pike</saddress><scity>Corryton</scity><sstate>TN</sstate><sbrand>UNBRANDED</sbrand><soctane>87 89 91</soctane></station><station><slat>36.17688</slat><slong>-83.80058</slong><sname>Pit Stop Market</sname><saddress>1650 Tazewell Pike</saddress><scity>Corryton</scity><sstate>TN</sstate><sbrand>UNBRANDED</sbrand><soctane>87 93</soctane></station><station><slat>35.46143</slat><slong>-83.16193</slong><sname>Massie's Country Market</sname><saddress>5040 Hooper HwyHwy 321</saddress><scity>Cosby</scity><sstate>TN</sstate><sbrand>UNBRANDED</sbrand><soctane>87</soctane></station><station><slat>35.04368</slat><slong>-88.26734</slong><sname>Jake's</sname><saddress>6580 Hwy 57</saddress><scity>Counce</scity><sstate>TN</sstate><sbrand>UNBRANDED</sbrand><soctane>87 89 93</soctane></station><station><slat>35.56363</slat><slong>-89.64998</slong><sname>Jimmy's Detail And Auto Service</sname><saddress>203 Highway 51 S.</saddress><scity>Covington</scity><sstate>TN</sstate><sbrand>UNBRANDED</sbrand><soctane>87</soctane></station><station><slat>35</slat><slong>-89</slong><sname>Tipton Co Oil Company</sname><saddress>515 Sanford Ave</saddress><scity>Covington</scity><sstate>TN</sstate><sbrand>UNBRANDED</sbrand><soctane>87</soctane></station><station><slat>35.55925</slat><slong>-89.64015</slong><sname>Wooten Oil Company</sname><saddress>513 Sanford Ave</saddress><scity>Covington</scity><sstate>TN</sstate><sbrand>UNBRANDED</sbrand><soctane>93</soctane></station><station><slat>35.16499</slat><slong>-86.01025</slong><sname>Linda's Market</sname><saddress>303 Cumberland St E</saddress><scity>Cowan</scity><sstate>TN</sstate><sbrand>UNBRANDED</sbrand><soctane>89 93</soctane></station><station><slat>35.95361</slat><slong>-85.00229</slong><sname>Food Mart Sunoco</sname><saddress>1390 Hwy 70 East</saddress><scity>Crossville</scity><sstate>TN</sstate><sbrand>UNBRANDED</sbrand><soctane>87</soctane></station><station><slat>36.05024</slat><slong>-85.14612</slong><sname>Sunoco Gas Station</sname><saddress>6461 Plateau Road</saddress><scity>Crossville</scity><sstate>TN</sstate><sbrand>SUNOCO</sbrand><soctane>87</soctane></station><station><slat>35.90731</slat><slong>-84.9706</slong><sname>Sawmill Market</sname><saddress>918 Hwy 68</saddress><scity>Crossville</scity><sstate>TN</sstate><sbrand>UNBRANDED</sbrand><soctane>87</soctane></station><station><slat>35.9466</slat><slong>-85.02366</slong><sname>Honey's Market</sname><saddress>Hwy 70</saddress><scity>Crossville</scity><sstate>TN</sstate><sbrand>UNBRANDED</sbrand><soctane>87</soctane></station><station><slat>35.48442</slat><slong>-85.02332</slong><sname>B &amp; E Convenience</sname><saddress>531 Market Street</saddress><scity>Dayton</scity><sstate>TN</sstate><sbrand>UNBRANDED</sbrand><soctane>87 89 93</soctane></station><station><slat>35.47497</slat><slong>-85.03086</slong><sname>American Trading Post</sname><saddress>4427 Rhea County Highway</saddress><scity>Dayton</scity><sstate>TN</sstate><sbrand>UNBRANDED</sbrand><soctane>87 89 93</soctane></station><station><slat>35.47056</slat><slong>-85.03541</slong><sname>Highway 27 Convenience And Gas</sname><saddress>4025 Rhea County Highway</saddress><scity>Dayton</scity><sstate>TN</sstate><sbrand>PHILLIPS</sbrand><soctane>87 89 91</soctane></station><station><slat>35.47027</slat><slong>-85.03448</slong><sname>Friendly Market</sname><saddress>4040 Rhea County Highway</saddress><scity>Dayton</scity><sstate>TN</sstate><sbrand>HI-TECH</sbrand><soctane>87</soctane></station><station><slat>36.0301</slat><slong>-87.43573</slong><sname>Village Market</sname><saddress>1664 Hwy 48 South</saddress><scity>Dickson</scity><sstate>TN</sstate><sbrand>UNBRANDED</sbrand><soctane>92</soctane></station><station><slat>36.04249</slat><slong>-87.34285</slong><sname>Old Columbia Mkt.</sname><saddress>1700 Old Columbia Rd</saddress><scity>Dickson</scity><sstate>TN</sstate><sbrand>UNBRANDED</sbrand><soctane>87 89 92</soctane></station><station><slat>36.5078</slat><slong>-87.83183</slong><sname>Pit Stop Market</sname><saddress>407 Highway 79</saddress><scity>Dover</scity><sstate>TN</sstate><sbrand>UNBRANDED</sbrand><soctane>87</soctane></station><station><slat>36.29141</slat><slong>-88.69548</slong><sname>Tj's Market</sname><saddress>461 East Main Street</saddress><scity>Dresden</scity><sstate>TN</sstate><sbrand>UNBRANDED</sbrand><soctane>87</soctane></station><station><slat>35.40133</slat><slong>-85.37102</slong><sname>Hi-Tech</sname><saddress>14904 Rankin Ave</saddress><scity>Dunlap</scity><sstate>TN</sstate><sbrand>HI-TECH</sbrand><soctane>87 89 92</soctane></station><station><slat>35.3592</slat><slong>-85.39712</slong><sname>The Little Store</sname><saddress>Hwy 28 And Jones Rd</saddress><scity>Dunlap</scity><sstate>TN</sstate><sbrand>SUNOCO</sbrand><soctane>86 89 91</soctane></station><station><slat>36.05415</slat><slong>-89.373</slong><sname>Kc's Onestop</sname><saddress>1012 Hwy 51 Bypass W</saddress><scity>Dyersburg</scity><sstate>TN</sstate><sbrand>UNBRANDED</sbrand><soctane>87 89 93</soctane></station><station><slat>35.11716</slat><slong>-89.72258</slong><sname>Canales Grocery</sname><saddress>10170 Raleigh Lagrange</saddress><scity>Eads</scity><sstate>TN</sstate><sbrand>UNBRANDED</sbrand><soctane>87 92</soctane></station><station><slat>35.75583</slat><slong>-86.64946</slong><sname>Farmer's Coop</sname><saddress>1217 N. Main St.</saddress><scity>Eagleville</scity><sstate>TN</sstate><sbrand>UNBRANDED</sbrand><soctane>87 89 93</soctane></station><station><slat>34.98948</slat><slong>-85.20915</slong><sname>Tip Top Food Mart</sname><saddress>6500 Ringgold Rd</saddress><scity>East Ridge</scity><sstate>TN</sstate><sbrand>UNBRANDED</sbrand><soctane>87 89 93</soctane></station><station><slat>36.31502</slat><slong>-82.19868</slong><sname>Greers Convenience</sname><saddress>3950 Highway 19 East</saddress><scity>Elizabethton</scity><sstate>TN</sstate><sbrand>UNBRANDED</sbrand><soctane>87 93</soctane></station><station><slat>36.35859</slat><slong>-82.2249</slong><sname>Hyder's Sunshine Market</sname><saddress>Snowbird Lane</saddress><scity>Elizabethton</scity><sstate>TN</sstate><sbrand>UNBRANDED</sbrand><soctane>87 89 93</soctane></station><station><slat>36.41612</slat><slong>-82.07633</slong><sname>A.D. Fletchers</sname><saddress>Hwy 91</saddress><scity>Elizabethton</scity><sstate>TN</sstate><sbrand>ADDCO</sbrand><soctane>87 93</soctane></station><station><slat>36.3514</slat><slong>-82.21553</slong><sname>Broad Street Volco</sname><saddress>Corner Broad &amp; Sycamore Streets</saddress><scity>Elizabethton</scity><sstate>TN</sstate><sbrand>VOLCO</sbrand><soctane>87 89 93</soctane></station><station><slat>36.32001</slat><slong>-82.20126</slong><sname>Valley View Market</sname><saddress>2608 Stateline Road</saddress><scity>Elizabethton</scity><sstate>TN</sstate><sbrand>VOLCO</sbrand><soctane>87 89 93</soctane></station><station><slat>36.39921</slat><slong>-82.23067</slong><sname>State Line Market</sname><saddress>1876 Highway 19e</saddress><scity>Elizabethton</scity><sstate>TN</sstate><sbrand>CITGO</sbrand><soctane>87 89 93</soctane></station><station><slat>36.33014</slat><slong>-82.26548</slong><sname>Holiday Market</sname><saddress>2226 West G Street</saddress><scity>Elizabethton</scity><sstate>TN</sstate><sbrand>UNBRANDED</sbrand><soctane>87 89 93</soctane></station><station><slat>36.12774</slat><slong>-82.42973</slong><sname>J.D.'s Market</sname><saddress>1313 Jackson Love Hwy (South Erwin)</saddress><scity>Erwin</scity><sstate>TN</sstate><sbrand>UNBRANDED</sbrand><soctane>87</soctane></station><station><slat>35.27198</slat><slong>-86.19323</slong><sname>Dunlap's Market</sname><saddress>8212 Old Tullahoma Road</saddress><scity>Estill Springs</scity><sstate>TN</sstate><sbrand>PURE</sbrand><soctane>89 93</soctane></station><station><slat>35.26581</slat><slong>-86.12498</slong><sname>Sak-N-Pak # 3</sname><saddress>500 S. Main St.</saddress><scity>Estill Springs</scity><sstate>TN</sstate><sbrand>UNBRANDED</sbrand><soctane>87 89 93</soctane></station><station><slat>35.32038</slat><slong>-87.29545</slong><sname>Marshall's Grocery</sname><saddress>3706 Hwy 43 N.</saddress><scity>Ethridge</scity><sstate>TN</sstate><sbrand>MARATHON</sbrand><soctane>90</soctane></station><station><slat>35.0903</slat><slong>-86.589</slong><sname>Bluebird's Market</sname><saddress>326 Ardmore Hwy</saddress><scity>Fayetteville</scity><sstate>TN</sstate><sbrand>UNBRANDED</sbrand><soctane>87</soctane></station><station><slat>35.16108</slat><slong>-86.55158</slong><sname>Lincoln County Farmers Coop</sname><saddress>1205 Winchester Hiway (Us 64)</saddress><scity>Fayetteville</scity><sstate>TN</sstate><sbrand>UNBRANDED</sbrand><soctane>87 89 93</soctane></station><station><slat>35.16455</slat><slong>-86.57777</slong><sname>Sammy's</sname><saddress>720 Lewisburg Hwy</saddress><scity>Fayetteville</scity><sstate>TN</sstate><sbrand>PURE</sbrand><soctane>87 89 93</soctane></station><station><slat>35.16275</slat><slong>-86.54607</slong><sname>Jj's Quick Stop</sname><saddress>1050 Winchester Hwy</saddress><scity>Fayetteville</scity><sstate>TN</sstate><sbrand>EXXON</sbrand><soctane>87 89 93</soctane></station><station><slat>35.89922</slat><slong>-86.87637</slong><sname>Market Master</sname><saddress>1814 Columbia Avenue</saddress><scity>Franklin</scity><sstate>TN</sstate><sbrand>PURE</sbrand><soctane>87 89 93</soctane></station><station><slat>35.91243</slat><slong>-86.88827</slong><sname>Garrets</sname><saddress>1411 West Main St.</saddress><scity>Franklin</scity><sstate>TN</sstate><sbrand>UNBRANDED</sbrand><soctane></soctane></station><station><slat>36.38669</slat><slong>-85.54228</slong><sname>Strong's Market</sname><saddress>3290 York Hwy</saddress><scity>Gainesboro</scity><sstate>TN</sstate><sbrand>UNBRANDED</sbrand><soctane>87 93</soctane></station><station><slat>36.39853</slat><slong>-86.35636</slong><sname>Highway 25 Market</sname><saddress>2542 Hartsville Pike</saddress><scity>Gallatin</scity><sstate>TN</sstate><sbrand>PHILLIPS</sbrand><soctane>91</soctane></station><station><slat>36.37704</slat><slong>-86.44051</slong><sname>Dean Oil Company</sname><saddress>203 James St.</saddress><scity>Gallatin</scity><sstate>TN</sstate><sbrand>UNBRANDED</sbrand><soctane>87 89 93</soctane></station><station><slat>36.22</slat><slong>-86.27</slong><sname>Kwik Sak</sname><saddress>611 Nashville Pike</saddress><scity>Gallatin</scity><sstate>TN</sstate><sbrand>UNBRANDED</sbrand><soctane>87 93</soctane></station><station><slat>35.28646</slat><slong>-84.94606</slong><sname>58 Short Stop</sname><saddress>3734 Hwy 58</saddress><scity>Georgetown</scity><sstate>TN</sstate><sbrand>CHEVRON</sbrand><soctane>87 89 93</soctane></station><station><slat>36.30679</slat><slong>-86.70359</slong><sname>B &amp; S Service Center</sname><saddress>601 Rivergate Pkwy.</saddress><scity>Goodlettsville</scity><sstate>TN</sstate><sbrand>UNBRANDED</sbrand><soctane>87 89 93</soctane></station><station><slat>35.64263</slat><slong>-84.14774</slong><sname>Greenback Corner Deli</sname><saddress>Tn 95 At Us Highway 411</saddress><scity>Greenback</scity><sstate>TN</sstate><sbrand>UNBRANDED</sbrand><soctane>87</soctane></station><station><slat>36.17616</slat><slong>-82.80765</slong><sname>Forest Hill Corner</sname><saddress>1302 Snapps Ferry Road</saddress><scity>Greeneville</scity><sstate>TN</sstate><sbrand>UNBRANDED</sbrand><soctane></soctane></station><station><slat>36.17604</slat><slong>-82.76782</slong><sname>Pioneer Market</sname><saddress>480 Erwin Hwy</saddress><scity>Greeneville</scity><sstate>TN</sstate><sbrand>UNBRANDED</sbrand><soctane></soctane></station><station><slat>36.04553</slat><slong>-84.341</slong><sname>Big E's Quik Mart</sname><saddress>116 Sroane St</saddress><scity>Harriman</scity><sstate>TN</sstate><sbrand>UNBRANDED</sbrand><soctane>87 89 92</soctane></station><station><slat>35.87543</slat><slong>-84.56973</slong><sname>Big E's Quick Mart</sname><saddress>2843 Roane State Hwy</saddress><scity>Harriman</scity><sstate>TN</sstate><sbrand>UNBRANDED</sbrand><soctane>87 92</soctane></station><station><slat>35.181</slat><slong>-85.06748</slong><sname>58 Mart</sname><saddress>8909 U.S. 58</saddress><scity>Harrison</scity><sstate>TN</sstate><sbrand>UNBRANDED</sbrand><soctane>87 89 91</soctane></station><station><slat>36.40224</slat><slong>-86.17428</slong><sname>Bubba's Market</sname><saddress>114 Mcmurry Blvd W.</saddress><scity>Hartsville</scity><sstate>TN</sstate><sbrand>SUNOCO</sbrand><soctane>87 89 93</soctane></station><station><slat>36.19228</slat><slong>-86.61997</slong><sname>Kwik Sak</sname><saddress>4890 Lebanon Rd</saddress><scity>Hermitage</scity><sstate>TN</sstate><sbrand>MARATHON</sbrand><soctane>87</soctane></station><station><slat>36.1681</slat><slong>-86.60056</slong><sname>Kwik Sak</sname><saddress>5835 Old Hickory Boulevard</saddress><scity>Hermitage</scity><sstate>TN</sstate><sbrand>KWIK</sbrand><soctane>87 89 93</soctane></station><station><slat>36.19487</slat><slong>-86.57399</slong><sname>Circle B</sname><saddress>1050 Old Lebanon Dirt Road</saddress><scity>Hermitage</scity><sstate>TN</sstate><sbrand>UNBRANDED</sbrand><soctane></soctane></station><station><slat>35.16848</slat><slong>-85.20855</slong><sname>Spur Market</sname><saddress>6802 Middle Valley Road</saddress><scity>Hixson</scity><sstate>TN</sstate><sbrand>UNBRANDED</sbrand><soctane>93</soctane></station><station><slat>35.19209</slat><slong>-85.18877</slong><sname>Middle Valley Pure</sname><saddress>7726 Middle Valley Road</saddress><scity>Hixson</scity><sstate>TN</sstate><sbrand>PURE</sbrand><soctane>87 92</soctane></station><station><slat>35.54976</slat><slong>-87.54298</slong><sname>Darins C Mart</sname><saddress>426 East Main Street</saddress><scity>Hohenwald</scity><sstate>TN</sstate><sbrand>UNBRANDED</sbrand><soctane>87 89 93</soctane></station><station><slat>36.00406</slat><slong>-88.41402</slong><sname>East End Service Center</sname><saddress>20435 Main Street East</saddress><scity>Huntingdon</scity><sstate>TN</sstate><sbrand>PURE</sbrand><soctane>87 89 92</soctane></station><station><slat>35.61701</slat><slong>-88.83778</slong><sname>Ragans</sname><saddress>412 Airways Blvd.</saddress><scity>Jackson</scity><sstate>TN</sstate><sbrand>CITGO</sbrand><soctane>87</soctane></station><station><slat>35.03856</slat><slong>-85.57926</slong><sname>Petro South #416</sname><saddress>8333 Hwy 41</saddress><scity>Jasper</scity><sstate>TN</sstate><sbrand>PETRO</sbrand><soctane>87</soctane></station><station><slat>36.11916</slat><slong>-83.50515</slong><sname>Lakeview Market</sname><saddress>296 W Old Andrew Johnson Highway</saddress><scity>Jefferson City</scity><sstate>TN</sstate><sbrand>UNBRANDED</sbrand><soctane>87 89 93</soctane></station><station><slat>36.3158</slat><slong>-86.86583</slong><sname>Heritage Travel Center</sname><saddress>7201 Whites Creek Pike</saddress><scity>Joelton</scity><sstate>TN</sstate><sbrand>UNBRANDED</sbrand><soctane>87</soctane></station><station><slat>36.31362</slat><slong>-82.37915</slong><sname>7 Star Stop</sname><saddress>1107 W Market St</saddress><scity>Johnson City</scity><sstate>TN</sstate><sbrand>UNBRANDED</sbrand><soctane>87 89 93</soctane></station><station><slat>36.3816</slat><slong>-82.36616</slong><sname>Zeke's Market</sname><saddress>3701 Bristol Hwy.</saddress><scity>Johnson City</scity><sstate>TN</sstate><sbrand>UNBRANDED</sbrand><soctane>87 93</soctane></station><station><slat>36.35322</slat><slong>-82.38186</slong><sname>North Roan Servicenter</sname><saddress>2601 N Roan St</saddress><scity>Johnson City</scity><sstate>TN</sstate><sbrand>VOLCO</sbrand><soctane>87</soctane></station><station><slat>36.27072</slat><slong>-82.31844</slong><sname>Volco</sname><saddress>Roan Street</saddress><scity>Johnson City</scity><sstate>TN</sstate><sbrand>UNBRANDED</sbrand><soctane>87 89 91</soctane></station><station><slat>36.32542</slat><slong>-82.56148</slong><sname>Trailblazer Market</sname><saddress>1519 Hwy 81 N</saddress><scity>Jonesborough</scity><sstate>TN</sstate><sbrand>MARATHON</sbrand><soctane>90</soctane></station><station><slat>36.28541</slat><slong>-82.48187</slong><sname>Washington Farmers Cooperative</sname><saddress>1001 Depot St</saddress><scity>Jonesborough</scity><sstate>TN</sstate><sbrand>UNBRANDED</sbrand><soctane>87</soctane></station><station><slat>36.22886</slat><slong>-82.44575</slong><sname>The Store</sname><saddress>4581 Cherokee Road</saddress><scity>Jonesborough</scity><sstate>TN</sstate><sbrand>UNBRANDED</sbrand><soctane>87 89 93</soctane></station><station><slat>36.34903</slat><slong>-82.54085</slong><sname>Sonny's Market</sname><saddress>1426 Gray/Sulphur Springs Rd.</saddress><scity>Jonesborough</scity><sstate>TN</sstate><sbrand>UNBRANDED</sbrand><soctane>87 89 93</soctane></station><station><slat>36.35391</slat><slong>-82.53469</slong><sname>Sulphur Springs Food Mart</sname><saddress>1301 Gray/Sulphur Springs Road</saddress><scity>Jonesborough</scity><sstate>TN</sstate><sbrand>UNBRANDED</sbrand><soctane>87 93</soctane></station><station><slat>36.5531</slat><slong>-82.57335</slong><sname>Shop-N-Go Market &amp; Deli</sname><saddress>798 W Center St.</saddress><scity>Kingsport</scity><sstate>TN</sstate><sbrand>UNBRANDED</sbrand><soctane>87</soctane></station><station><slat>36.52816</slat><slong>-82.53583</slong><sname>Bays Market</sname><saddress>813 N. Eastman Road</saddress><scity>Kingsport</scity><sstate>TN</sstate><sbrand>UNBRANDED</sbrand><soctane>87 89 93</soctane></station><station><slat>36.5439</slat><slong>-82.55297</slong><sname>Center Dale Service Center</sname><saddress>801 East Center Street</saddress><scity>Kingsport</scity><sstate>TN</sstate><sbrand>UNBRANDED</sbrand><soctane>87</soctane></station><station><slat>36.53689</slat><slong>-82.525</slong><sname>M &amp; M Mart</sname><saddress>1571 N. Eastman Rd.</saddress><scity>Kingsport</scity><sstate>TN</sstate><sbrand>UNBRANDED</sbrand><soctane>87 90 93</soctane></station><station><slat>36.45302</slat><slong>-82.46611</slong><sname>Apple Shed</sname><saddress>5526 Fort Henry Dr</saddress><scity>Kingsport</scity><sstate>TN</sstate><sbrand>UNBRANDED</sbrand><soctane>87 89 93</soctane></station><station><slat>36.56476</slat><slong>-82.45565</slong><sname>Rite Quick</sname><saddress>3337 East Stone Drive</saddress><scity>Kingsport</scity><sstate>TN</sstate><sbrand>UNBRANDED</sbrand><soctane>87 93</soctane></station><station><slat>35.92982</slat><slong>-84.00102</slong><sname>Smoky Mountain Market</sname><saddress>357 Northshore Drive</saddress><scity>Knoxville</scity><sstate>TN</sstate><sbrand>UNBRANDED</sbrand><soctane>87</soctane></station><station><slat>35.91398</slat><slong>-83.82909</slong><sname>Korner Market</sname><saddress>7512 Sevierville Pike</saddress><scity>Knoxville</scity><sstate>TN</sstate><sbrand>UNBRANDED</sbrand><soctane>87</soctane></station><station><slat>35.90905</slat><slong>-83.84767</slong><sname>Us Fuel Plus</sname><saddress>7345 Chapman Hwy</saddress><scity>Knoxville</scity><sstate>TN</sstate><sbrand>UNBRANDED</sbrand><soctane>87 89 93</soctane></station><station><slat>36.01528</slat><slong>-83.96671</slong><sname>Weigel's #35</sname><saddress>300 Cedar Ln</saddress><scity>Knoxville</scity><sstate>TN</sstate><sbrand>WEIGEL'S</sbrand><soctane>87 89 92</soctane></station><station><slat>36.12071</slat><slong>-83.85333</slong><sname>Weigels # 39</sname><saddress>7420 Tazewell Pike</saddress><scity>Knoxville</scity><sstate>TN</sstate><sbrand>WEIGEL'S</sbrand><soctane>87 88 92</soctane></station><station><slat>35.90438</slat><slong>-84.07241</slong><sname>Weigels # 34</sname><saddress>600 Ebenezer Road</saddress><scity>Knoxville</scity><sstate>TN</sstate><sbrand>WEIGEL'S</sbrand><soctane>87 89 92</soctane></station><station><slat>36.06754</slat><slong>-83.97009</slong><sname>Weigels #20</sname><saddress>2119 W Emory Road</saddress><scity>Knoxville</scity><sstate>TN</sstate><sbrand>WEIGEL'S</sbrand><soctane>87 89 92</soctane></station><station><slat>36.0167</slat><slong>-83.82634</slong><sname>Breadbox Food Stores</sname><saddress>6210 Asheville Highway</saddress><scity>Knoxville</scity><sstate>TN</sstate><sbrand>SHELL</sbrand><soctane>93</soctane></station><station><slat>35.99001</slat><slong>-83.93985</slong><sname>Fresh Mart &amp; Deli</sname><saddress>2418 North Central Street</saddress><scity>Knoxville</scity><sstate>TN</sstate><sbrand>UNBRANDED</sbrand><soctane>87</soctane></station><station><slat>35.92894</slat><slong>-84.0009</slong><sname>Ci Rcle M</sname><saddress>401 S. Northshore Drive</saddress><scity>Knoxville</scity><sstate>TN</sstate><sbrand>UNBRANDED</sbrand><soctane>87 89 92</soctane></station><station><slat>36.00509</slat><slong>-83.85525</slong><sname>Kwik Pantry</sname><saddress>4800 Asheville Hwy</saddress><scity>Knoxville</scity><sstate>TN</sstate><sbrand>UNBRANDED</sbrand><soctane>87 89 92</soctane></station><station><slat>35.92109</slat><slong>-83.875</slong><sname>Kwik Pantry</sname><saddress>6222 Chapman Hwy</saddress><scity>Knoxville</scity><sstate>TN</sstate><sbrand>UNBRANDED</sbrand><soctane>87 92</soctane></station><station><slat>35.85322</slat><slong>-84.09662</slong><sname>Weigel's Farm Store</sname><saddress>10103 S Northshore Dr</saddress><scity>Knoxville</scity><sstate>TN</sstate><sbrand>WEIGEL'S</sbrand><soctane>87 89 92</soctane></station><station><slat>36.01618</slat><slong>-83.86239</slong><sname>Spring Hill Market</sname><saddress>5016 Rutledge Pk.</saddress><scity>Knoxville</scity><sstate>TN</sstate><sbrand>UNBRANDED</sbrand><soctane>87 89 93</soctane></station><station><slat>36.52828</slat><slong>-86.02648</slong><sname>Macon-Trousdale Farmers Co-Op</sname><saddress>905 Scottsville Rd.</saddress><scity>Lafayette</scity><sstate>TN</sstate><sbrand>UNBRANDED</sbrand><soctane>87</soctane></station><station><slat>36.53341</slat><slong>-86.08788</slong><sname>Coley's Market</sname><saddress>3982 Highway 52 E</saddress><scity>Lafayette</scity><sstate>TN</sstate><sbrand>KEY</sbrand><soctane>87 89 93</soctane></station><station><slat>36.5192</slat><slong>-86.025</slong><sname>Mixon Nollner</sname><saddress>306 Red Boiling Springs Rd</saddress><scity>Lafayette</scity><sstate>TN</sstate><sbrand>KEY</sbrand><soctane>87 89 93</soctane></station><station><slat>36.51819</slat><slong>-86.02026</slong><sname>Express Lane Market</sname><saddress>212 Highway 52 By-Pass East</saddress><scity>Lafayette</scity><sstate>TN</sstate><sbrand>MARATHON</sbrand><soctane>90</soctane></station><station><slat>36.22671</slat><slong>-84.15033</slong><sname>John's Food Market</sname><saddress>104 Cobb Hollow Rd.</saddress><scity>Lake City</scity><sstate>TN</sstate><sbrand>SUNOCO</sbrand><soctane></soctane></station><station><slat>36.25468</slat><slong>-86.09709</slong><sname>Whites Service Station</sname><saddress>915 Lebanon Hwy.</saddress><scity>Lebanon</scity><sstate>TN</sstate><sbrand>PURE</sbrand><soctane>87 89 92</soctane></station><station><slat>36.2021</slat><slong>-86.29192</slong><sname>Quik-N-Easy</sname><saddress>313 S Cumberland St</saddress><scity>Lebanon</scity><sstate>TN</sstate><sbrand>PURE</sbrand><soctane>87 89 93</soctane></station><station><slat>36.33317</slat><slong>-86.43628</slong><sname>Lakeside Market</sname><saddress>10680 Highway 109</saddress><scity>Lebanon</scity><sstate>TN</sstate><sbrand>UNBRANDED</sbrand><soctane>87 89</soctane></station><station><slat>36.29226</slat><slong>-86.4438</slong><sname>Home Run Market</sname><saddress>7790 Highway 109 N</saddress><scity>Lebanon</scity><sstate>TN</sstate><sbrand>UNBRANDED</sbrand><soctane>87 89</soctane></station><station><slat>36.23277</slat><slong>-86.38437</slong><sname>Franklin's Market</sname><saddress>3961 Lebanon Rd</saddress><scity>Lebanon</scity><sstate>TN</sstate><sbrand>UNBRANDED</sbrand><soctane>87 91 93</soctane></station><station><slat>36.21786</slat><slong>-86.32629</slong><sname>Wilson Co-Op Your Hometown Store</sname><saddress>107 Babb Drive</saddress><scity>Lebanon</scity><sstate>TN</sstate><sbrand>UNBRANDED</sbrand><soctane>87 90 93</soctane></station><station><slat>35.89563</slat><slong>-86.9952</slong><sname>Pucketts Grocery</sname><saddress>4142 Old Hillsboro Rd.</saddress><scity>Leipers Fork</scity><sstate>TN</sstate><sbrand>UNBRANDED</sbrand><soctane>87 89 93</soctane></station><station><slat>35.84132</slat><slong>-84.3002</slong><sname>Luttrell's Service Station</sname><saddress>5139 Highway 321 N</saddress><scity>Lenoir City</scity><sstate>TN</sstate><sbrand>UNBRANDED</sbrand><soctane></soctane></station><station><slat>35.83209</slat><slong>-84.34363</slong><sname>Dutton's Grocery</sname><saddress>4527 Kingston Highway</saddress><scity>Lenoir City</scity><sstate>TN</sstate><sbrand>UNBRANDED</sbrand><soctane>87 93</soctane></station><station><slat>35.5298</slat><slong>-86.8239</slong><sname>Berlin Store Country Market (U S 431)</sname><saddress>2460 Lewisburg And Franklin Pk</saddress><scity>Lewisburg</scity><sstate>TN</sstate><sbrand>UNBRANDED</sbrand><soctane>87</soctane></station><station><slat>35.4433</slat><slong>-86.79234</slong><sname>Fairview Market</sname><saddress>616 Cornersville Rd</saddress><scity>Lewisburg</scity><sstate>TN</sstate><sbrand>UNBRANDED</sbrand><soctane>87 89 93</soctane></station><station><slat>35.43897</slat><slong>-86.77435</slong><sname>Marshall Farmer's Co-Op</sname><saddress>615 S. Ellington Pkwy</saddress><scity>Lewisburg</scity><sstate>TN</sstate><sbrand>UNBRANDED</sbrand><soctane></soctane></station><station><slat>35.65126</slat><slong>-88.39269</slong><sname>Block And Barrel Food Stop</sname><saddress>50 North Broad Street</saddress><scity>Lexington</scity><sstate>TN</sstate><sbrand>UNBRANDED</sbrand><soctane>87</soctane></station><station><slat>35.63623</slat><slong>-88.26781</slong><sname>Fisher's Grocery &amp; Wrecker Service</sname><saddress>20400 Hwy 412 East</saddress><scity>Lexington</scity><sstate>TN</sstate><sbrand>UNBRANDED</sbrand><soctane>87 89 93</soctane></station><station><slat>36.38594</slat><slong>-85.33504</slong><sname>Carr Gas</sname><saddress>2120 Bradford Hicks Drive</saddress><scity>Livingston</scity><sstate>TN</sstate><sbrand>UNBRANDED</sbrand><soctane>87 89 93</soctane></station><station><slat>35.07376</slat><slong>-87.44036</slong><sname>Corner Mini-Mart</sname><saddress>220 S Military St</saddress><scity>Loretto</scity><sstate>TN</sstate><sbrand>PHILLIPS</sbrand><soctane>93</soctane></station><station><slat>35.73445</slat><slong>-84.40227</slong><sname>Stop N' Shop</sname><saddress>16471 Highway 72n</saddress><scity>Loudon</scity><sstate>TN</sstate><sbrand>UNBRANDED</sbrand><soctane>87</soctane></station><station><slat>35.7398</slat><slong>-84.33577</slong><sname>Loudon Market</sname><saddress>700 Grove St.</saddress><scity>Loudon</scity><sstate>TN</sstate><sbrand>UNBRANDED</sbrand><soctane>87 89 91</soctane></station><station><slat>35.73971</slat><slong>-84.33931</slong><sname>Gt Oil Inc</sname><saddress>700 Mulberry St</saddress><scity>Loudon</scity><sstate>TN</sstate><sbrand>MARATHON</sbrand><soctane>87 93</soctane></station><station><slat>35.78936</slat><slong>-84.10196</slong><sname>Ians Market</sname><saddress>3108 Ralph Phelps Road</saddress><scity>Louisville</scity><sstate>TN</sstate><sbrand>UNBRANDED</sbrand><soctane>87</soctane></station><station><slat>35.53007</slat><slong>-86.08099</slong><sname>Green's Best Way</sname><saddress>3030 Woodbury Hwy</saddress><scity>Manchester</scity><sstate>TN</sstate><sbrand>UNBRANDED</sbrand><soctane>87 89 91</soctane></station><station><slat>35.52982</slat><slong>-86.01258</slong><sname>Jimmy's Mini Market</sname><saddress>5506 Mcminnville Hwy</saddress><scity>Manchester</scity><sstate>TN</sstate><sbrand>SUNOCO</sbrand><soctane>87 89 93</soctane></station><station><slat>35.49044</slat><slong>-86.09639</slong><sname>Hilltop Market &amp; Grill</sname><saddress>1334 Murfreesboro Highway</saddress><scity>Manchester</scity><sstate>TN</sstate><sbrand>PHILLIPS</sbrand><soctane>87 88 92</soctane></station><station><slat>35.49495</slat><slong>-86.07054</slong><sname>J&amp;K Travel &amp; Convenience</sname><saddress>1421 Mcminnville Highway</saddress><scity>Manchester</scity><sstate>TN</sstate><sbrand>UNBRANDED</sbrand><soctane>87 89 93</soctane></station><station><slat>36.35324</slat><slong>-88.84906</slong><sname>Sudden Service Store</sname><saddress>509 North Lindell Street</saddress><scity>Martin</scity><sstate>TN</sstate><sbrand>UNBRANDED</sbrand><soctane>87</soctane></station><station><slat>35.7602</slat><slong>-83.96696</slong><sname>Zoomers</sname><saddress>107 Waahington St</saddress><scity>Maryville</scity><sstate>TN</sstate><sbrand>UNBRANDED</sbrand><soctane>87</soctane></station><station><slat>35.71472</slat><slong>-83.92045</slong><sname>Hill Market</sname><saddress>3302 Wilkerson Pike</saddress><scity>Maryville</scity><sstate>TN</sstate><sbrand>UNBRANDED</sbrand><soctane>89 93</soctane></station><station><slat>35.73156</slat><slong>-84.02876</slong><sname>Foothills Food Mart</sname><saddress>2740 Morganton Road</saddress><scity>Maryville</scity><sstate>TN</sstate><sbrand>PHILLPS</sbrand><soctane>87 89 93</soctane></station><station><slat>35.75647</slat><slong>-83.97046</slong><sname>Co-Op Fuel Center</sname><saddress>Us 129s (Hwy 411) At Westside Drive</saddress><scity>Maryville</scity><sstate>TN</sstate><sbrand>UNBRANDED</sbrand><soctane>93</soctane></station><station><slat>36.23438</slat><slong>-83.83977</slong><sname>Heiskell's</sname><saddress>2835 Maynardville Hwy</saddress><scity>Maynardville</scity><sstate>TN</sstate><sbrand>BP</sbrand><soctane>87 89 93</soctane></station><station><slat>35.11301</slat><slong>-84.98145</slong><sname>Mcdoanld Quick Stop</sname><saddress>4793 South Lee Highway</saddress><scity>Mcdonald</scity><sstate>TN</sstate><sbrand>UNBRANDED</sbrand><soctane>87</soctane></station><station><slat>36.1079</slat><slong>-87.63416</slong><sname>P &amp; D Quick Stop</sname><saddress>9554 Highway 70 East</saddress><scity>Mcewen</scity><sstate>TN</sstate><sbrand>UNBRANDED</sbrand><soctane>87</soctane></station><station><slat>36.13057</slat><slong>-88.50752</slong><sname>Eagle Food Store</sname><saddress>15980 North Highland Drive</saddress><scity>Mckenzie</scity><sstate>TN</sstate><sbrand>UNBRANDED</sbrand><soctane>87 89 93</soctane></station><station><slat>35.65851</slat><slong>-85.78939</slong><sname>Warren Farmers Co-Op</sname><saddress>1839 S Chancery St</saddress><scity>Mcminnville</scity><sstate>TN</sstate><sbrand>UNBRANDED</sbrand><soctane></soctane></station><station><slat>35.69557</slat><slong>-85.81409</slong><sname>Sue's Newtown Qwik Pic Mkt &amp; Cafe</sname><saddress>2615 Nashville Hwy</saddress><scity>Mcminnville</scity><sstate>TN</sstate><sbrand>UNBRANDED</sbrand><soctane>87 89 93</soctane></station><station><slat>36.1755</slat><slong>-84.1427</slong><sname>Ferguson's Gathering Place</sname><saddress>2655 Lake City Hwy</saddress><scity>Medford</scity><sstate>TN</sstate><sbrand>UNBRANDED</sbrand><soctane>87 88 89</soctane></station><station><slat>35.13408</slat><slong>-89.99028</slong><sname>Ballingers</sname><saddress>2124 Union Ave At Cooper</saddress><scity>Memphis</scity><sstate>TN</sstate><sbrand>UNBRANDED</sbrand><soctane>87</soctane></station><station><slat>35.11712</slat><slong>-89.72287</slong><sname>Canale &amp; Sons Grocery</sname><saddress>10170 Raleigh Lagrange Rd East</saddress><scity>Memphis-Eads</scity><sstate>TN</sstate><sbrand>UNBRANDED</sbrand><soctane>87 93</soctane></station><station><slat>36.14289</slat><slong>-85.27457</slong><sname>Monterey Citgo</sname><saddress>804 South Holly St</saddress><scity>Monterey</scity><sstate>TN</sstate><sbrand>CITGO</sbrand><soctane>87</soctane></station><station><slat>36.21218</slat><slong>-83.29083</slong><sname>Don's Service Center</sname><saddress>102 E Morris Blvd.</saddress><scity>Morristown</scity><sstate>TN</sstate><sbrand>UNBRANDED</sbrand><soctane>87 89 93</soctane></station><station><slat>36.23343</slat><slong>-83.24133</slong><sname>Hamblen Farmers Co-Op</sname><saddress>4048 East Morris Boulevard</saddress><scity>Morristown</scity><sstate>TN</sstate><sbrand>UNBRANDED</sbrand><soctane>87 89 93</soctane></station><station><slat>36.47391</slat><slong>-81.80239</slong><sname>Tri State Growers Co-Op</sname><saddress>101 Depot Street</saddress><scity>Mountain City</scity><sstate>TN</sstate><sbrand>UNBRANDED</sbrand><soctane>87 89 93</soctane></station><station><slat>36.46946</slat><slong>-81.80398</slong><sname>Lazy Day Market</sname><saddress>517 South Church Street</saddress><scity>Mountain City</scity><sstate>TN</sstate><sbrand>RUSH</sbrand><soctane>87 89 93</soctane></station><station><slat>36.44493</slat><slong>-81.79931</slong><sname>Roan Valley Market</sname><saddress>240 Roan Creek Road</saddress><scity>Mountain City</scity><sstate>TN</sstate><sbrand>RUSH</sbrand><soctane>87 89 93</soctane></station><station><slat>36.11896</slat><slong>-86.49524</slong><sname>Fastrack Market &amp; Deli</sname><saddress>1200 S Mount Juliet Rd</saddress><scity>Mt. Juliet</scity><sstate>TN</sstate><sbrand>UNBRANDED</sbrand><soctane>87 89 93</soctane></station><station><slat>36.25585</slat><slong>-86.5588</slong><sname>Mapco</sname><saddress>5550 Saundersville Rd.</saddress><scity>Mt. Juliet</scity><sstate>TN</sstate><sbrand>MAPCO</sbrand><soctane>87 89 91</soctane></station><station><slat>36.1984</slat><slong>-86.5042</slong><sname>Mapco</sname><saddress>4337 Saundersville Rd.</saddress><scity>Mt. Juliet</scity><sstate>TN</sstate><sbrand>MAPCO</sbrand><soctane>87 89 91</soctane></station><station><slat>36.11896</slat><slong>-86.49524</slong><sname>Suggs Creek Market</sname><saddress>4429 Stewarts Ferry</saddress><scity>Mt. Juliet</scity><sstate>TN</sstate><sbrand>UNBRANDED</sbrand><soctane>87 89 93</soctane></station><station><slat>36.19496</slat><slong>-86.5739</slong><sname>Circle B</sname><saddress>1050 Old Lebanon Road</saddress><scity>Mt. Juliet</scity><sstate>TN</sstate><sbrand>UNBRANDED</sbrand><soctane></soctane></station><station><slat>35.44749</slat><slong>-89.81158</slong><sname>Pop's Full Service</sname><saddress>1297 Munford Ave</saddress><scity>Munford</scity><sstate>TN</sstate><sbrand>UNBRANDED</sbrand><soctane>87 89 93</soctane></station><station><slat>35.4473</slat><slong>-89.81173</slong><sname>Pop's Amoco</sname><saddress>1313 Munford-Atoka</saddress><scity>Munford</scity><sstate>TN</sstate><sbrand>AMOCO</sbrand><soctane>87 89 93</soctane></station><station><slat>35.82721</slat><slong>-86.39151</slong><sname>Rutherford Cnty Farmers Co-Op</sname><saddress>980 Middle Tennessee Boulevard</saddress><scity>Murfreesboro</scity><sstate>TN</sstate><sbrand>CO-OP</sbrand><soctane>87 89 92</soctane></station><station><slat>35.93351</slat><slong>-86.43146</slong><sname>Leanna Market</sname><saddress>4303 Sulphur Springs Rd</saddress><scity>Murfreesboro</scity><sstate>TN</sstate><sbrand>UNBRANDED</sbrand><soctane>87</soctane></station><station><slat>35.84789</slat><slong>-86.39575</slong><sname>Captain Z</sname><saddress>500 College Ave</saddress><scity>Murfreesboro</scity><sstate>TN</sstate><sbrand>UNBRANDED</sbrand><soctane>87 89 93</soctane></station><station><slat>35.88964</slat><slong>-86.34061</slong><sname>Lascassas Market</sname><saddress>2712 Lascassas Pike</saddress><scity>Murfreesboro</scity><sstate>TN</sstate><sbrand>UNBRANDED</sbrand><soctane>87 89 93</soctane></station><station><slat>36.19273</slat><slong>-86.74438</slong><sname>Market Mac's</sname><saddress>1301 Gallatin Avenue</saddress><scity>Nashville</scity><sstate>TN</sstate><sbrand>UNBRANDED</sbrand><soctane></soctane></station><station><slat>36.08238</slat><slong>-86.75845</slong><sname>Ben Little Pure</sname><saddress>4663 Trousdale Drive</saddress><scity>Nashville</scity><sstate>TN</sstate><sbrand>PURE</sbrand><soctane>87 89 93</soctane></station><station><slat>36.061</slat><slong>-86.71702</slong><sname>Sloan's</sname><saddress>5001 Nolensville Pk</saddress><scity>Nashville</scity><sstate>TN</sstate><sbrand>PURE</sbrand><soctane>87 93</soctane></station><station><slat>36.20737</slat><slong>-86.77799</slong><sname>Bc Gas</sname><saddress>2312 Brick Church Pike</saddress><scity>Nashville</scity><sstate>TN</sstate><sbrand>UNBRANDED</sbrand><soctane>87 89 92</soctane></station><station><slat>36.16319</slat><slong>-86.85052</slong><sname>Wings &amp; Gas</sname><saddress>5205 Centennial Blvd</saddress><scity>Nashville</scity><sstate>TN</sstate><sbrand>UNBRANDED</sbrand><soctane>87 89 93</soctane></station><station><slat>36.15904</slat><slong>-86.8183</slong><sname>Swett's Market</sname><saddress>704 28th Ave. N.</saddress><scity>Nashville</scity><sstate>TN</sstate><sbrand>UNBRANDED</sbrand><soctane>87 89 93</soctane></station><station><slat>35.97175</slat><slong>-83.27227</slong><sname>Newport Citgo</sname><saddress>1321 W Hwy 25-70</saddress><scity>Newport</scity><sstate>TN</sstate><sbrand>CITGO</sbrand><soctane></soctane></station><station><slat>36.19367</slat><slong>-84.0726</slong><sname>Norris Service Center</sname><saddress>12 West Norris Road</saddress><scity>Norris</scity><sstate>TN</sstate><sbrand>UNBRANDED</sbrand><soctane>87 89 91</soctane></station><station><slat>35.1926</slat><slong>-84.88499</slong><sname>Corner Exit Market</sname><saddress>2550 Westside Drive</saddress><scity>Nw</scity><sstate>TN</sstate><sbrand>TEXACO</sbrand><soctane>87 92 93</soctane></station><station><slat>36.00395</slat><slong>-84.24046</slong><sname>Oak Ridge Sunoco</sname><saddress>270 Midway Ln.</saddress><scity>Oak Ridge</scity><sstate>TN</sstate><sbrand>SUNOCO</sbrand><soctane>92</soctane></station><station><slat>35.98751</slat><slong>-84.313</slong><sname>Weigel's</sname><saddress>2385 Oak Ridge Turnpike</saddress><scity>Oak Ridge</scity><sstate>TN</sstate><sbrand>SUNOCO</sbrand><soctane></soctane></station><station><slat>36.02675</slat><slong>-84.23772</slong><sname>Eddie Hair Tire &amp; Auto Center</sname><saddress>798 Oak Ridge Turnpike</saddress><scity>Oak Ridge</scity><sstate>TN</sstate><sbrand>UNBRANDED</sbrand><soctane>87 89 93</soctane></station><station><slat>36.16756</slat><slong>-89.23941</slong><sname>Obion Farmers Co-Op</sname><saddress>525 Palestine Road</saddress><scity>Obion</scity><sstate>TN</sstate><sbrand>UNBRANDED</sbrand><soctane>87</soctane></station><station><slat>36.23018</slat><slong>-86.58869</slong><sname>Mapco Express</sname><saddress>4337 Saundersville Rd</saddress><scity>Old Hickory</scity><sstate>TN</sstate><sbrand>MAPCO</sbrand><soctane>87 89 91</soctane></station><station><slat>35.5303</slat><slong>-84.9116</slong><sname>Sullivan's Mkt &amp; Deli</sname><saddress>Tenn Hiway 30 (Old Washington Rd)</saddress><scity>Old Washington</scity><sstate>TN</sstate><sbrand>UNBRANDED</sbrand><soctane></soctane></station><station><slat>36.51558</slat><slong>-84.50691</slong><sname>Big Orange Country Store</sname><saddress>19803 Alberta St.  (Us 27)</saddress><scity>Oneida</scity><sstate>TN</sstate><sbrand>UNBRANDED</sbrand><soctane>87 93</soctane></station><station><slat>35.21559</slat><slong>-85.03025</slong><sname>Elders Market</sname><saddress>10000 Hwy 58</saddress><scity>Ooltewah</scity><sstate>TN</sstate><sbrand>CONOCO</sbrand><soctane>87 89 93</soctane></station><station><slat>36.4365</slat><slong>-87.47787</slong><sname>Palmyra Mkt.</sname><saddress>2504 Hwy 149</saddress><scity>Palmyra</scity><sstate>TN</sstate><sbrand>UNBRANDED</sbrand><soctane>87</soctane></station><station><slat>35.69089</slat><slong>-85.32705</slong><sname>A&amp;H Market</sname><saddress>13255 Park Road</saddress><scity>Pikeville</scity><sstate>TN</sstate><sbrand>UNBRANDED</sbrand><soctane>87</soctane></station><station><slat>36.37924</slat><slong>-85.94956</slong><sname>Pleasant Shade Restaurant &amp; Grocery</sname><saddress>725 Pleasant Shade Hwy.</saddress><scity>Pleasant Shade</scity><sstate>TN</sstate><sbrand>UNBRANDED</sbrand><soctane>85 90</soctane></station><station><slat>36.02807</slat><slong>-84.03262</slong><sname>Weigel's Farm Store</sname><saddress>2119 West Emory Rd</saddress><scity>Powell</scity><sstate>TN</sstate><sbrand>UNBRANDED</sbrand><soctane>87 89 93</soctane></station><station><slat>35.15257</slat><slong>-87.04918</slong><sname>Winner's Circle</sname><saddress>1176 Bethel Rd</saddress><scity>Pulaski</scity><sstate>TN</sstate><sbrand>MARATHON</sbrand><soctane>90</soctane></station><station><slat>35.82985</slat><slong>-86.28999</slong><sname>Russell's Market</sname><saddress>5410 Old Woodbury Hwy</saddress><scity>Readyville</scity><sstate>TN</sstate><sbrand>UNBRANDED</sbrand><soctane>87 89</soctane></station><station><slat>36.14916</slat><slong>-82.10135</slong><sname>Jack's Grocery</sname><saddress>1235 Hwy. 143</saddress><scity>Roan Mountain</scity><sstate>TN</sstate><sbrand>UNBRANDED</sbrand><soctane>87 93</soctane></station><station><slat>35.79284</slat><slong>-85.61274</slong><sname>Rock Island Market</sname><saddress>1231 Rock Island Rd</saddress><scity>Rock Island</scity><sstate>TN</sstate><sbrand>UNBRANDED</sbrand><soctane>89</soctane></station><station><slat>35.86916</slat><slong>-84.68206</slong><sname>Big E's Quikmart</sname><saddress>326 N Gateway Ave</saddress><scity>Rockwood</scity><sstate>TN</sstate><sbrand>UNBRANDED</sbrand><soctane>87 89 92</soctane></station><station><slat>36.41856</slat><slong>-82.95696</slong><sname>Hawkins Farmer's Co-Op</sname><saddress>240 Burem Pike</saddress><scity>Rogersville</scity><sstate>TN</sstate><sbrand>UNBRANDED</sbrand><soctane></soctane></station><station><slat>36.24781</slat><slong>-82.59574</slong><sname>Liberty Market</sname><saddress>1100 E Main St</saddress><scity>Rogersville</scity><sstate>TN</sstate><sbrand>ZOOMERS</sbrand><soctane>87 89 93</soctane></station><station><slat>35.15615</slat><slong>-88.57856</slong><sname>Jim's Best Stop</sname><saddress>633 Mulberry Ave.</saddress><scity>Selmer</scity><sstate>TN</sstate><sbrand>UNBRANDED</sbrand><soctane>87 89 93</soctane></station><station><slat>35.80602</slat><slong>-83.45873</slong><sname>Dunns Market And Grill</sname><saddress>2650 Upper Middle Creek Road</saddress><scity>Sevierville</scity><sstate>TN</sstate><sbrand>UNBRANDED</sbrand><soctane>87 93</soctane></station><station><slat>35.87047</slat><slong>-83.57059</slong><sname>Sevier Farmers Co-Op</sname><saddress>321 W Main Street</saddress><scity>Sevierville</scity><sstate>TN</sstate><sbrand>UNBRANDED</sbrand><soctane>87 90 93</soctane></station><station><slat>35.19488</slat><slong>-85.91782</slong><sname>Sewanee Auto</sname><saddress>University Avenue</saddress><scity>Sewanee</scity><sstate>TN</sstate><sbrand>UNBRANDED</sbrand><soctane>87 93</soctane></station><station><slat>35.88019</slat><slong>-83.74268</slong><sname>White Star</sname><saddress>705 Boyds Creek Hwy</saddress><scity>Seymour</scity><sstate>TN</sstate><sbrand>UNBRANDED</sbrand><soctane>87 89 93</soctane></station><station><slat>35.47811</slat><slong>-86.39579</slong><sname>Pit Stop Market</sname><saddress>2134 Highway 64 W (Lewisburg Hwy)</saddress><scity>Shelbyville</scity><sstate>TN</sstate><sbrand>PURE</sbrand><soctane>87 93</soctane></station><station><slat>36.10375</slat><slong>-85.81956</slong><sname>Big Rock Market</sname><saddress>1193 Wolf Creek  Road</saddress><scity>Silver Point</scity><sstate>TN</sstate><sbrand>UNBRANDED</sbrand><soctane></soctane></station><station><slat>35.95727</slat><slong>-85.8164</slong><sname>Dekalb Tire &amp; Service</sname><saddress>200 East Broad St.</saddress><scity>Smithville</scity><sstate>TN</sstate><sbrand>PURE</sbrand><soctane>87 89 93</soctane></station><station><slat>35.95727</slat><slong>-85.8164</slong><sname>Kwik &amp; Ezy</sname><saddress>201 East Broad Street</saddress><scity>Smithville</scity><sstate>TN</sstate><sbrand>UNBRANDED</sbrand><soctane>87 89 93</soctane></station><station><slat>35.95471</slat><slong>-86.4944</slong><sname>Marathon</sname><saddress>406 S Lowry St</saddress><scity>Smyrna</scity><sstate>TN</sstate><sbrand>MARATHON</sbrand><soctane>90</soctane></station><station><slat>35.95023</slat><slong>-86.51021</slong><sname>Trading Post Market</sname><saddress>10412 Old Nashville Hwy</saddress><scity>Smyrna</scity><sstate>TN</sstate><sbrand>CITGO</sbrand><soctane></soctane></station><station><slat>35.97776</slat><slong>-86.52639</slong><sname>Emart</sname><saddress>300 Enon Springs Rd E</saddress><scity>Smyrna</scity><sstate>TN</sstate><sbrand>EMART</sbrand><soctane>87 89 93</soctane></station><station><slat>35.99626</slat><slong>-86.49232</slong><sname>Gil's Market</sname><saddress>100 Gils St.</saddress><scity>Smyrna</scity><sstate>TN</sstate><sbrand>UNBRANDED</sbrand><soctane>87 89 92</soctane></station><station><slat>35.23988</slat><slong>-85.15271</slong><sname>Green Pond Corner Grocery</sname><saddress>9823 Dallas Hollow Rd</saddress><scity>Soddy-Daisy</scity><sstate>TN</sstate><sbrand>UNBRANDED</sbrand><soctane>87</soctane></station><station><slat>36.24372</slat><slong>-85.95343</slong><sname>Mixon-Nollner Oil Company</sname><saddress>30 Cookeville Hwy. (Us Hwy 70n)</saddress><scity>South Carthage</scity><sstate>TN</sstate><sbrand>MOBIL</sbrand><soctane>87 89 93</soctane></station><station><slat>36.50182</slat><slong>-88.89342</slong><sname>Pipeline Products Llc</sname><saddress>1102 Chickasaw Drive (Hwy 45/51)</saddress><scity>South Fulton</scity><sstate>TN</sstate><sbrand>UNBRANDED</sbrand><soctane>87</soctane></station><station><slat>35.0123</slat><slong>-85.70442</slong><sname>Walker Oil Company</sname><saddress>107 3rd Street</saddress><scity>South Pittsburg</scity><sstate>TN</sstate><sbrand>HI-TECH</sbrand><soctane>87 89 93</soctane></station><station><slat>35.75621</slat><slong>-83.96345</slong><sname>A To Z  Gas</sname><saddress>605</saddress><scity>South Washington Street</scity><sstate>TN</sstate><sbrand>UNBRANDED</sbrand><soctane>87 89 93</soctane></station><station><slat>35.92256</slat><slong>-85.4809</slong><sname>Coop</sname><saddress>271 Mayberry St</saddress><scity>Sparta</scity><sstate>TN</sstate><sbrand>UNBRANDED</sbrand><soctane></soctane></station><station><slat>35.98448</slat><slong>-85.49574</slong><sname>Jose's</sname><saddress>1714 Roberts-Matthews Hwy.</saddress><scity>Sparta</scity><sstate>TN</sstate><sbrand>SUNOCO</sbrand><soctane>87 89 92</soctane></station><station><slat>35.6229</slat><slong>-85.42365</slong><sname>The Way Inn</sname><saddress>1989 Archie Rhinehart Parkway</saddress><scity>Spencer</scity><sstate>TN</sstate><sbrand>UNBRANDED</sbrand><soctane>87 93</soctane></station><station><slat>35.70127</slat><slong>-84.8678</slong><sname>Big Apple Market</sname><saddress>1543 Wassom Memorial Hwy</saddress><scity>Spring City</scity><sstate>TN</sstate><sbrand>UNBRANDED</sbrand><soctane>87 89 93</soctane></station><station><slat>35.70215</slat><slong>-86.89879</slong><sname>Walls Grocery</sname><saddress>4170 Kedron Road</saddress><scity>Spring Hill</scity><sstate>TN</sstate><sbrand>UNBRANDED</sbrand><soctane>85</soctane></station><station><slat>35.69266</slat><slong>-86.88619</slong><sname>The Old Oak</sname><saddress>4383 Kedron Road</saddress><scity>Spring Hill</scity><sstate>TN</sstate><sbrand>UNBRANDED</sbrand><soctane>87</soctane></station><station><slat>36.49852</slat><slong>-86.88195</slong><sname>C &amp; D Market</sname><saddress>1609 Memorial Blvd.</saddress><scity>Springfield</scity><sstate>TN</sstate><sbrand>MYSTIK</sbrand><soctane>87 89 93</soctane></station><station><slat>36.5031</slat><slong>-86.88488</slong><sname>Dean Oil Company</sname><saddress>104 11th Avenue East</saddress><scity>Springfield</scity><sstate>TN</sstate><sbrand>UNBRANDED</sbrand><soctane>87 89 93</soctane></station><station><slat>35.43935</slat><slong>-87.29152</slong><sname>Matheny's Market</sname><saddress>69 State Highway 20 Scn</saddress><scity>Summertown</scity><sstate>TN</sstate><sbrand>PURE</sbrand><soctane></soctane></station><station><slat>35.54739</slat><slong>-84.06648</slong><sname>Smokey Mtn Harley Davidson Tallassee</sname><saddress>5908 Calderwood Hwy (U.S. 129)</saddress><scity>Tallassee</scity><sstate>TN</sstate><sbrand>UNBRANDED</sbrand><soctane>87 89 93</soctane></station><station><slat>35.62391</slat><slong>-84.76212</slong><sname>Lakeside Marine Sales</sname><saddress>2782 State Highway 304</saddress><scity>Ten Mile</scity><sstate>TN</sstate><sbrand>UNBRANDED</sbrand><soctane>87</soctane></station><station><slat>35.3766</slat><slong>-88.2021</slong><sname>Saltillo Landing Cafe</sname><saddress>25 Shoreline LaneSaltillo</saddress><scity>Tn 38370</scity><sstate>TN</sstate><sbrand>UNBRANDED</sbrand><soctane>87 89 93</soctane></station><station><slat>35.98095</slat><slong>-88.94325</slong><sname>Lewis West End Tire Company</sname><saddress>301 W. Eaton Street</saddress><scity>Trenton</scity><sstate>TN</sstate><sbrand>UNBRANDED</sbrand><soctane>87</soctane></station><station><slat>35.29139</slat><slong>-86.21252</slong><sname>S &amp; J General Store</sname><saddress>10021 Old Tullahoma Rd</saddress><scity>Tullahoma</scity><sstate>TN</sstate><sbrand>UNBRANDED</sbrand><soctane>87 89</soctane></station><station><slat>36.20907</slat><slong>-82.34703</slong><sname>Jerry's Market</sname><saddress>4205 Unicoi Drive</saddress><scity>Unicoi</scity><sstate>TN</sstate><sbrand>UNBRANDED</sbrand><soctane></soctane></station><station><slat>36.43292</slat><slong>-89.04624</slong><sname>Kwik Food Mart</sname><saddress>1005 North Clover Street</saddress><scity>Union City</scity><sstate>TN</sstate><sbrand>UNBRANDED</sbrand><soctane>87 91</soctane></station><station><slat>36.43341</slat><slong>-89.06283</slong><sname>Obion Farmers Co-Op</sname><saddress>810 Mt. Zion Rd.</saddress><scity>Union City</scity><sstate>TN</sstate><sbrand>UNBRANDED</sbrand><soctane>87</soctane></station><station><slat>35.61173</slat><slong>-84.20297</slong><sname>Vics Full Service</sname><saddress>Us Highway 411</saddress><scity>Vonore</scity><sstate>TN</sstate><sbrand>UNBRANDED</sbrand><soctane>87 90 93</soctane></station><station><slat>36.36761</slat><slong>-82.25442</slong><sname>The Barn Shoppe</sname><saddress>450 Watauga Road</saddress><scity>Watauga</scity><sstate>TN</sstate><sbrand>UNBRANDED</sbrand><soctane>87 93</soctane></station><station><slat>36.09788</slat><slong>-86.13324</slong><sname>Three Forks Market Place</sname><saddress>9000 Sparta Pike</saddress><scity>Watertown</scity><sstate>TN</sstate><sbrand>UNBRANDED</sbrand><soctane>87 89 93</soctane></station><station><slat>36.08425</slat><slong>-87.77071</slong><sname>J Market</sname><saddress>800 E Main St</saddress><scity>Waverly</scity><sstate>TN</sstate><sbrand>UNBRANDED</sbrand><soctane>87 89 93</soctane></station><station><slat>36.05592</slat><slong>-87.77884</slong><sname>Humphreys Farmer's Cooperative</sname><saddress>2173 Highway 13 South</saddress><scity>Waverly</scity><sstate>TN</sstate><sbrand>UNBRANDED</sbrand><soctane></soctane></station><station><slat>36.5338</slat><slong>-86.18929</slong><sname>Peggy's Market</sname><saddress>10329 Hwy 52 West</saddress><scity>Westmoreland</scity><sstate>TN</sstate><sbrand>MARATHON</sbrand><soctane>87 93</soctane></station><station><slat>36.12637</slat><slong>-87.22723</slong><sname>Lucky's Market</sname><saddress>2286 Hwy 47 North</saddress><scity>White Bluff</scity><sstate>TN</sstate><sbrand>MARATHON</sbrand><soctane>90</soctane></station><station><slat>36.18578</slat><slong>-87.16608</slong><sname>Mary Helen's</sname><saddress>2101 Claylick Road</saddress><scity>White Bluff</scity><sstate>TN</sstate><sbrand>UNBRANDED</sbrand><soctane>87 93</soctane></station><station><slat>35.19888</slat><slong>-86.12232</slong><sname>J &amp; J Creekside Market</sname><saddress>1303 North High Street</saddress><scity>Winchester</scity><sstate>TN</sstate><sbrand>UNBRANDED</sbrand><soctane>89 93</soctane></station><station><slat>35.18535</slat><slong>-86.16708</slong><sname>Easy Food Mart</sname><saddress>3395 Lynchburg Road</saddress><scity>Winchester</scity><sstate>TN</sstate><sbrand>UNBRANDED</sbrand><soctane>87 89 90</soctane></station><station><slat>35.18559</slat><slong>-86.19972</slong><sname>Broadview Grocery</sname><saddress>5324 Lynchburg Rd</saddress><scity>Winchester</scity><sstate>TN</sstate><sbrand>AMOCO</sbrand><soctane>87 89 93</soctane></station><station><slat>35.82769</slat><slong>-86.06316</slong><sname>Davenport Service Station</sname><saddress>335 Mcminnville Hwy</saddress><scity>Woodbury</scity><sstate>TN</sstate><sbrand>UNBRANDED</sbrand><soctane>87 89 93</soctane></station><station><slat>35.82738</slat><slong>-86.06201</slong><sname>Farmers Co-Op</sname><saddress>400 Mcminnville Hwy</saddress><scity>Woodbury</scity><sstate>TN</sstate><sbrand>UNBRANDED</sbrand><soctane>87 89 93</soctane></station><station><slat>35.63685</slat><slong>-88.84796</slong><sname>Poplar Corner Exxon</sname><saddress>1450 Hollywood Dr</saddress><scity></scity><sstate>TN</sstate><sbrand>EXXON</sbrand><soctane>87</soctane></station></stations>